Metadata-Version: 1.0
Name: nbody.py
Version: 0.0.2
Summary: Modulo de simulación para n-cuerpos
Home-page: UNKNOWN
Author: Javier Urrutia
Author-email: UNKNOWN
License: UNKNOWN
Platform: UNKNOWN
